{
    "data":[
        {
            "curl": "curl -X GET \"https://api.spaceflightnewsapi.net/v4/articles/\"",
            "description": "This curl command retrieves a list of articles from the Spaceflight News API. It returns a paginated list of articles based on the query parameters provided, allowing you to filter and paginate through the articles."
        },
        {
            "curl": "curl -X GET \"https://api.spaceflightnewsapi.net/v4/articles/{id}/\"",
            "description": "This curl command retrieves a specific article from the Spaceflight News API based on the unique ID provided in the URL. It allows you to access the details of a single article."
        }
    ]
}